evathon/__init__.py
evathon/custom.py
evathon/functions.py
evathon/helpers.py
evathon/hints.py
evathon/password.py
evathon/requestiter.py
evathon/sync.py
evathon/types.py
evathon/utils.py
evathon/version.py
evathon/_updates/__init__.py
evathon/_updates/entitycache.py
evathon/_updates/messagebox.py
evathon/_updates/session.py
evathon/client/__init__.py
evathon/client/account.py
evathon/client/auth.py
evathon/client/bots.py
evathon/client/buttons.py
evathon/client/chats.py
evathon/client/dialogs.py
evathon/client/downloads.py
evathon/client/messageparse.py
evathon/client/messages.py
evathon/client/telegrambaseclient.py
evathon/client/telegramclient.py
evathon/client/updates.py
evathon/client/uploads.py
evathon/client/users.py
evathon/crypto/__init__.py
evathon/crypto/aes.py
evathon/crypto/aesctr.py
evathon/crypto/authkey.py
evathon/crypto/cdndecrypter.py
evathon/crypto/factorization.py
evathon/crypto/libssl.py
evathon/crypto/rsa.py
evathon/errors/__init__.py
evathon/errors/common.py
evathon/errors/rpcbaseerrors.py
evathon/errors/rpcerrorlist.py
evathon/events/__init__.py
evathon/events/album.py
evathon/events/callbackquery.py
evathon/events/chataction.py
evathon/events/common.py
evathon/events/inlinequery.py
evathon/events/messagedeleted.py
evathon/events/messageedited.py
evathon/events/messageread.py
evathon/events/newmessage.py
evathon/events/raw.py
evathon/events/userupdate.py
evathon/extensions/__init__.py
evathon/extensions/binaryreader.py
evathon/extensions/html.py
evathon/extensions/markdown.py
evathon/extensions/messagepacker.py
evathon/network/__init__.py
evathon/network/authenticator.py
evathon/network/mtprotoplainsender.py
evathon/network/mtprotosender.py
evathon/network/mtprotostate.py
evathon/network/requeststate.py
evathon/network/connection/__init__.py
evathon/network/connection/connection.py
evathon/network/connection/http.py
evathon/network/connection/tcpabridged.py
evathon/network/connection/tcpfull.py
evathon/network/connection/tcpintermediate.py
evathon-2.3.1.dist-info/licenses/LICENSE
evathon-2.3.1.dist-info/METADATA
evathon-2.3.1.dist-info/WHEEL
evathon-2.3.1.dist-info/top_level.txt
evathon-2.3.1.dist-info/RECORD
